llm_webextract-1.2.4.dist-info/licenses/LICENSE
tests/__init__.py
tests/test_basic.py
webextract/__init__.py
webextract/cli.py
webextract/config/__init__.py
webextract/config/profiles.py
webextract/config/settings.py
webextract/core/__init__.py
webextract/core/anthropic_client.py
webextract/core/exceptions.py
webextract/core/extractor.py
webextract/core/llm_client.py
webextract/core/llm_factory.py
webextract/core/models.py
webextract/core/openai_client.py
webextract/core/scraper.py
llm_webextract-1.2.4.dist-info/METADATA
llm_webextract-1.2.4.dist-info/WHEEL
llm_webextract-1.2.4.dist-info/entry_points.txt
llm_webextract-1.2.4.dist-info/top_level.txt
llm_webextract-1.2.4.dist-info/RECORD
